projectcard/__init__.py
projectcard/docs.py
projectcard/errors.py
projectcard/io.py
projectcard/logger.py
projectcard/projectcard.py
projectcard/update.py
projectcard/utils.py
projectcard/validate.py
projectcard/bin/update_projectcard_schema
projectcard/bin/validate_card
projectcard/examples/roadway-add-delete.yml
projectcard/examples/roadway-add-interchange.yml
projectcard/examples/roadway-add-managed-lane-restricted-access.yml
projectcard/examples/roadway-add-managed-lane-simple.yml
projectcard/examples/roadway-add.yml
projectcard/examples/roadway-calculated.wr
projectcard/examples/roadway-delete.yml
projectcard/examples/roadway-node-property-change.yml
projectcard/examples/roadway-property-change-all.yml
projectcard/examples/roadway-property-change.yml
projectcard/examples/transit-node-selection.yml
projectcard/examples/transit-property-change.yml
projectcard/examples/transit-route_addition.yml
projectcard/examples/transit-service_deletion.yml
projectcard/examples/transit-shape-change.yml
projectcard/models/__init__.py
projectcard/models/_base.py
projectcard/models/changes.py
projectcard/models/fields.py
projectcard/models/project.py
projectcard/models/selections.py
projectcard/models/structs.py
projectcard/models/time.py
projectcard/schema/projectcard.json
projectcard/schema/changes/roadway_addition.json
projectcard/schema/changes/roadway_deletion.json
projectcard/schema/changes/roadway_property_change.json
projectcard/schema/changes/transit_property_change.json
projectcard/schema/changes/transit_route_addition.json
projectcard/schema/changes/transit_routing_change.json
projectcard/schema/changes/transit_service_deletion.json
projectcard/schema/changes/defs/property_set.json
projectcard/schema/changes/defs/scoped_property_set.json
projectcard/schema/defs/dependencies.json
projectcard/schema/defs/mode.json
projectcard/schema/defs/tags.json
projectcard/schema/defs/time.json
projectcard/schema/defs/timespan.json
projectcard/schema/roadway/roadway_link.json
projectcard-0.3.3.dist-info/LICENSE
projectcard-0.3.3.dist-info/METADATA
projectcard-0.3.3.dist-info/WHEEL
projectcard-0.3.3.dist-info/top_level.txt
projectcard-0.3.3.dist-info/RECORD
