Metadata-Version: 2.1
Name: projectcard
Version: 0.3.3
Summary: Project Cards represent information about a tranportation infrastructure projects sufficient for usage in a regional travel demand model. This package supports validation and usage of this schema.
Author-email: Elizabeth Sall <elizabeth@urbanlabs.io>
License: Apache License
Classifier: Development Status :: 1 - Planning
Classifier: License :: OSI Approved :: Apache Software License
Classifier: Natural Language :: English
Classifier: Operating System :: OS Independent
Classifier: Programming Language :: Python
Classifier: Programming Language :: Python :: 3
Requires-Python: >=3.9
License-File: LICENSE
Requires-Dist: jsonref
Requires-Dist: jsonschema
Requires-Dist: pydantic>=2.0
Requires-Dist: pyyaml
Requires-Dist: tabulate
Requires-Dist: ruff
Requires-Dist: toml
